{".class":"MypyFile","_fullname":"ropt.plugins.base","future_import_flags":["annotations"],"is_partial_stub_package":false,"is_stub":false,"names":{".class":"SymbolTable","ABC":{".class":"SymbolTableNode","cross_ref":"abc.ABC","kind":"Gdef","module_hidden":true,"module_public":false},"Plugin":{".class":"SymbolTableNode","kind":"Gdef","node":{".class":"TypeInfo","_promote":[],"abstract_attributes":[["is_supported",1]],"alt_promote":null,"bases":["abc.ABC"],"dataclass_transform_spec":null,"declared_metaclass":null,"defn":{".class":"ClassDef","fullname":"ropt.plugins.base.Plugin","name":"Plugin","type_vars":[]},"deletable_attributes":[],"deprecated":null,"flags":["is_abstract"],"fullname":"ropt.plugins.base.Plugin","has_param_spec_type":false,"metaclass_type":"abc.ABCMeta","metadata":{},"module_name":"ropt.plugins.base","mro":["ropt.plugins.base.Plugin","abc.ABC","builtins.object"],"names":{".class":"SymbolTable","allows_discovery":{".class":"SymbolTableNode","kind":"Mdef","node":{".class":"Decorator","func":{".class":"FuncDef","abstract_status":0,"arg_kinds":[0],"arg_names":["cls"],"dataclass_transform_spec":null,"deprecated":null,"flags":["is_class","is_decorated","is_trivial_self"],"fullname":"ropt.plugins.base.Plugin.allows_discovery","name":"allows_discovery","type":{".class":"CallableType","arg_kinds":[0],"arg_names":["cls"],"arg_types":[{".class":"TypeType","item":"ropt.plugins.base.Plugin"}],"def_extras":{"first_arg":"cls"},"fallback":"builtins.function","from_concatenate":false,"implicit":false,"imprecise_arg_kinds":false,"is_bound":false,"is_ellipsis_args":false,"name":"allows_discovery of Plugin","ret_type":"builtins.bool","type_guard":null,"type_is":null,"unpack_kwargs":false,"variables":[]}},"is_overload":false,"var":{".class":"Var","flags":["is_initialized_in_class","is_classmethod","is_ready","is_inferred"],"fullname":"ropt.plugins.base.Plugin.allows_discovery","name":"allows_discovery","setter_type":null,"type":{".class":"CallableType","arg_kinds":[0],"arg_names":["cls"],"arg_types":[{".class":"TypeType","item":"ropt.plugins.base.Plugin"}],"def_extras":{"first_arg":"cls"},"fallback":"builtins.function","from_concatenate":false,"implicit":false,"imprecise_arg_kinds":false,"is_bound":false,"is_ellipsis_args":false,"name":"allows_discovery of Plugin","ret_type":"builtins.bool","type_guard":null,"type_is":null,"unpack_kwargs":false,"variables":[]}}}},"is_supported":{".class":"SymbolTableNode","kind":"Mdef","node":{".class":"Decorator","func":{".class":"FuncDef","abstract_status":1,"arg_kinds":[0,0],"arg_names":["cls","method"],"dataclass_transform_spec":null,"deprecated":null,"flags":["is_class","is_decorated","is_trivial_body","is_trivial_self"],"fullname":"ropt.plugins.base.Plugin.is_supported","name":"is_supported","type":{".class":"CallableType","arg_kinds":[0,0],"arg_names":["cls","method"],"arg_types":[{".class":"TypeType","item":"ropt.plugins.base.Plugin"},"builtins.str"],"def_extras":{"first_arg":"cls"},"fallback":"builtins.function","from_concatenate":false,"implicit":false,"imprecise_arg_kinds":false,"is_bound":false,"is_ellipsis_args":false,"name":"is_supported of Plugin","ret_type":"builtins.bool","type_guard":null,"type_is":null,"unpack_kwargs":false,"variables":[]}},"is_overload":false,"var":{".class":"Var","flags":["is_initialized_in_class","is_classmethod","is_ready","is_inferred"],"fullname":"ropt.plugins.base.Plugin.is_supported","name":"is_supported","setter_type":null,"type":{".class":"CallableType","arg_kinds":[0,0],"arg_names":["cls","method"],"arg_types":[{".class":"TypeType","item":"ropt.plugins.base.Plugin"},"builtins.str"],"def_extras":{"first_arg":"cls"},"fallback":"builtins.function","from_concatenate":false,"implicit":false,"imprecise_arg_kinds":false,"is_bound":false,"is_ellipsis_args":false,"name":"is_supported of Plugin","ret_type":"builtins.bool","type_guard":null,"type_is":null,"unpack_kwargs":false,"variables":[]}}}}},"self_type":{".class":"TypeVarType","default":{".class":"AnyType","missing_import_name":null,"source_any":null,"type_of_any":4},"fullname":"ropt.plugins.base.Plugin.Self","id":0,"name":"Self","namespace":"","upper_bound":"ropt.plugins.base.Plugin","values":[],"variance":0},"slots":null,"tuple_type":null,"type_vars":[],"typeddict_type":null}},"__annotations__":{".class":"SymbolTableNode","kind":"Gdef","node":{".class":"Var","flags":["is_ready"],"fullname":"ropt.plugins.base.__annotations__","name":"__annotations__","setter_type":null,"type":{".class":"Instance","args":["builtins.str",{".class":"AnyType","missing_import_name":null,"source_any":null,"type_of_any":6}],"extra_attrs":null,"type_ref":"builtins.dict"}}},"__doc__":{".class":"SymbolTableNode","kind":"Gdef","node":{".class":"Var","flags":["is_ready"],"fullname":"ropt.plugins.base.__doc__","name":"__doc__","setter_type":null,"type":"builtins.str"}},"__file__":{".class":"SymbolTableNode","kind":"Gdef","node":{".class":"Var","flags":["is_ready"],"fullname":"ropt.plugins.base.__file__","name":"__file__","setter_type":null,"type":"builtins.str"}},"__name__":{".class":"SymbolTableNode","kind":"Gdef","node":{".class":"Var","flags":["is_ready"],"fullname":"ropt.plugins.base.__name__","name":"__name__","setter_type":null,"type":"builtins.str"}},"__package__":{".class":"SymbolTableNode","kind":"Gdef","node":{".class":"Var","flags":["is_ready"],"fullname":"ropt.plugins.base.__package__","name":"__package__","setter_type":null,"type":"builtins.str"}},"__spec__":{".class":"SymbolTableNode","kind":"Gdef","node":{".class":"Var","flags":["is_ready"],"fullname":"ropt.plugins.base.__spec__","name":"__spec__","setter_type":null,"type":"_frozen_importlib.ModuleSpec"}},"abstractmethod":{".class":"SymbolTableNode","cross_ref":"abc.abstractmethod","kind":"Gdef","module_hidden":true,"module_public":false},"annotations":{".class":"SymbolTableNode","cross_ref":"__future__.annotations","kind":"Gdef","module_hidden":true,"module_public":false}},"path":"/home/verveerpj/ert-dev/ropt/src/ropt/plugins/base.py"}